{
    "title": "Parsippany -Troy Hills STEM Pathways",
    "outline": [
        {
            "level": "H2",
            "text": "Goals:",
            "page": 1
        },
        {
            "level": "H1",
            "text": "PATHWAY  OPTIONS",
            "page": 1
        },
        {
            "level": "H1",
            "text": "REGULAR  PATHWAY                 DISTINCTION PATHWAY",
            "page": 1
        },
        {
            "level": "H2",
            "text": "Science/Technology Class",
            "page": 1
        }
    ],
    "extraction_timestamp": "2025-07-28T09:03:34.465631",
    "total_headings": 4
}